datastream_direct/__init__.py
datastream_direct/api_client.py
datastream_direct/connection.py
datastream_direct/cursor.py
datastream_direct/exceptions.py
datastream_direct/models.py
datastream_direct/pandas_extras.py
datastream_direct/spotfire_extras.py
datastream_direct-0.1.4.dist-info/METADATA
datastream_direct-0.1.4.dist-info/WHEEL
datastream_direct-0.1.4.dist-info/licenses/LICENSE
datastream_direct-0.1.4.dist-info/RECORD
