Metadata-Version: 2.4
Name: datastream_direct
Version: 0.1.4
Summary: Python client for DataStream Direct API
Project-URL: Homepage, https://energydomain.com/data
Author-email: Energy Domain <developers@energydomain.com>
License: Attribution-NonCommercial-NoDerivatives 4.0 International
License-File: LICENSE
Keywords: api,client,database,datastream,sql
Classifier: Development Status :: 4 - Beta
Classifier: Intended Audience :: Developers
Classifier: License :: Free for non-commercial use
Classifier: Programming Language :: Python :: 3
Classifier: Programming Language :: Python :: 3.7
Classifier: Programming Language :: Python :: 3.8
Classifier: Programming Language :: Python :: 3.9
Classifier: Programming Language :: Python :: 3.10
Classifier: Programming Language :: Python :: 3.11
Classifier: Programming Language :: Python :: 3.12
Classifier: Topic :: Database
Classifier: Topic :: Software Development :: Libraries :: Python Modules
Requires-Python: >=3.7
Requires-Dist: pandas>=1.0.0
Requires-Dist: requests>=2.25.0
Requires-Dist: typing-extensions>=3.10.0; python_version < '3.8'
Requires-Dist: urllib3>=1.26.5
Provides-Extra: dev
Requires-Dist: black>=21.0.0; extra == 'dev'
Requires-Dist: flake8>=3.8.0; extra == 'dev'
Requires-Dist: isort>=5.0.0; extra == 'dev'
Requires-Dist: mypy>=0.800; extra == 'dev'
Requires-Dist: pytest-cov>=2.10.0; extra == 'dev'
Requires-Dist: pytest>=6.0.0; extra == 'dev'
Provides-Extra: spotfire
Requires-Dist: spotfire>=1.9.0; extra == 'spotfire'
